Loading_Bar/example.py
Loading_Bar/loadingBar.py
LoadingBar_Py_Diggs-0.1.1.dist-info/LICENSE
LoadingBar_Py_Diggs-0.1.1.dist-info/METADATA
LoadingBar_Py_Diggs-0.1.1.dist-info/WHEEL
LoadingBar_Py_Diggs-0.1.1.dist-info/top_level.txt
LoadingBar_Py_Diggs-0.1.1.dist-info/RECORD
