Metadata-Version: 2.1
Name: LoadingBar-Py-Diggs
Version: 0.1.1
Summary: A Simple loading bar for python.
Author-email: Vetle Hollund <vetlehoo@gmail.com>
Project-URL: Homepage, https://github.com/VHollund/LoadingBar
Project-URL: Bug Reports, https://github.com/VHollund/LoadingBar/issues
Classifier: Programming Language :: Python :: 3
Classifier: License :: OSI Approved :: MIT License
Classifier: Operating System :: OS Independent
Requires-Python: >=3.7
License-File: LICENSE
